<?xml version="1.0" encoding="UTF-8" ?><!DOCTYPE dokumente SYSTEM "http://www.gesetze-im-internet.de/dtd/1.01/gii-norm.dtd">
<dokumente builddate="20161007120716" doknr="BJNR170700004"><norm builddate="20161007120716" doknr="BJNR170700004"><metadaten><jurabk>WiPrPrüfV</jurabk><amtabk>WiPrPrüfV</amtabk><ausfertigung-datum manuell="ja">2004-07-20</ausfertigung-datum><fundstelle typ="amtlich"><periodikum>BGBl I</periodikum><zitstelle>2004, 1707</zitstelle></fundstelle><kurzue>Wirtschaftsprüferprüfungsverordnung</kurzue><langue>Prüfungsverordnung für Wirtschaftsprüfer nach §§ 14 und 131l der Wirtschaftsprüferordnung</langue><standangabe checked="ja"><standtyp>Stand</standtyp><standkommentar>Zuletzt geändert durch Art. 2 V v. 6.7.2016 I 1615</standkommentar></standangabe></metadaten><textdaten><fussnoten><Content><P><BR/> <pre xml:space="preserve">(+++ Textnachweis ab: 24. 7.2004 +++)<BR/><BR/></pre></P></Content></fussnoten></textdaten></norm>
<norm builddate="20161007120716" doknr="BJNR170700004BJNE000100000"><metadaten><jurabk>WiPrPrüfV</jurabk><enbez>Eingangsformel</enbez></metadaten><textdaten><text format="XML"><Content><P>Auf Grund der §§ 14 und 131l der Wirtschaftsprüferordnung in der Fassung der Bekanntmachung vom 5. November 1975 (BGBl. I S. 2803), § 14 zuletzt geändert durch Artikel 1 Nr. 13 und § 131l zuletzt geändert durch Artikel 1 Nr. 65 des Gesetzes vom 1. Dezember 2003 (BGBl. I S. 2446), verordnet das Bundesministerium für Wirtschaft und Arbeit:</P></Content></text></textdaten></norm>
<norm builddate="20161007120716" doknr="BJNR170700004BJNE000201118"><metadaten><jurabk>WiPrPrüfV</jurabk><enbez>Inhaltsübersicht</enbez></metadaten><textdaten><text format="XML"><Content><P><table frame="none" pgwide="1" tocentry="%yes;"><tgroup align="left" char="" charoff="50" cols="3" colsep="0" rowsep="0"><colspec colname="col1" colnum="1" colwidth="5*"/><colspec colname="col2" colnum="2" colwidth="20*"/><colspec colname="col3" colnum="3" colwidth="85*"/><tbody valign="top"><row><entry VJ="1" align="left" colsep="0" nameend="col3" namest="col1" valign="top">Erster Teil</entry></row><row><entry VJ="1" align="left" colsep="0" valign="top"> </entry><entry VJ="1" align="left" colsep="0" nameend="col3" namest="col2" valign="top">Prüfungsverfahren nach §14 der Wirtschaftsprüferordnung</entry></row><row><entry VJ="1" align="left" colsep="0" nameend="col2" namest="col1" valign="top">§ 1</entry><entry VJ="1" align="left" colsep="0" valign="top">Antrag auf Zulassung zur Prüfung</entry></row><row><entry VJ="1" align="left" colsep="0" nameend="col2" namest="col1" valign="top">§ 2</entry><entry VJ="1" align="left" colsep="0" valign="top">Prüfungskommission, Prüfungstermine</entry></row><row><entry VJ="1" align="left" colsep="0" nameend="col2" namest="col1" valign="top">§ 3</entry><entry VJ="1" align="left" colsep="0" valign="top">Berufung der Mitglieder der Prüfungskommission</entry></row><row><entry VJ="1" align="left" colsep="0" nameend="col2" namest="col1" valign="top">§ 4</entry><entry VJ="1" align="left" colsep="0" valign="top">Prüfungsgebiete</entry></row><row><entry VJ="1" nameend="col2" namest="col1">§ 4a</entry><entry VJ="1">Prüfungsgebiete der verkürzten Prüfung nach § 13a der Wirtschaftsprüferordnung</entry></row><row><entry VJ="1" align="left" colsep="0" nameend="col2" namest="col1" valign="top">§ 5</entry><entry VJ="1" align="left" colsep="0" valign="top">Gliederung der Prüfung</entry></row><row><entry VJ="1" align="left" colsep="0" nameend="col2" namest="col1" valign="top">§ 6</entry><entry VJ="1" align="left" colsep="0" valign="top">Verkürzte Prüfung</entry></row><row><entry VJ="1" align="left" colsep="0" nameend="col2" namest="col1" valign="top">§ 7</entry><entry VJ="1" align="left" colsep="0" valign="top">Schriftliche Prüfung</entry></row><row><entry VJ="1" align="left" colsep="0" nameend="col2" namest="col1" valign="top">§ 8</entry><entry VJ="1" align="left" colsep="0" valign="top">Aufgabenkommission</entry></row><row><entry VJ="1" align="left" colsep="0" nameend="col2" namest="col1" valign="top">§ 9</entry><entry VJ="1" align="left" colsep="0" valign="top">Widerspruchskommission</entry></row><row><entry VJ="1" align="left" colsep="0" nameend="col2" namest="col1" valign="top">§ 10</entry><entry VJ="1" align="left" colsep="0" valign="top">Aufsichtsarbeiten</entry></row><row><entry VJ="1" align="left" colsep="0" nameend="col2" namest="col1" valign="top">§ 11</entry><entry VJ="1" align="left" colsep="0" valign="top">Prüfungsnoten</entry></row><row><entry VJ="1" align="left" colsep="0" nameend="col2" namest="col1" valign="top">§ 12</entry><entry VJ="1" align="left" colsep="0" valign="top">Bewertung der Aufsichtsarbeiten</entry></row><row><entry VJ="1" align="left" colsep="0" nameend="col2" namest="col1" valign="top">§ 13</entry><entry VJ="1" align="left" colsep="0" valign="top">Ergebnis der schriftlichen Prüfung; Ausschluss von der mündlichen Prüfung</entry></row><row><entry VJ="1" align="left" colsep="0" nameend="col2" namest="col1" valign="top">§ 14</entry><entry VJ="1" align="left" colsep="0" valign="top">Vorberatung der Prüfungskommission</entry></row><row><entry VJ="1" align="left" colsep="0" nameend="col2" namest="col1" valign="top">§ 15</entry><entry VJ="1" align="left" colsep="0" valign="top">Mündliche Prüfung</entry></row><row><entry VJ="1" align="left" colsep="0" nameend="col2" namest="col1" valign="top">§ 16</entry><entry VJ="1" align="left" colsep="0" valign="top">Bewertung der mündlichen Prüfung</entry></row><row><entry VJ="1" align="left" colsep="0" nameend="col2" namest="col1" valign="top">§ 17</entry><entry VJ="1" align="left" colsep="0" valign="top">Prüfungsgesamtnote</entry></row><row><entry VJ="1" align="left" colsep="0" nameend="col2" namest="col1" valign="top">§ 18</entry><entry VJ="1" align="left" colsep="0" valign="top">Prüfungsergebnis</entry></row><row><entry VJ="1" align="left" colsep="0" nameend="col2" namest="col1" valign="top">§ 19</entry><entry VJ="1" align="left" colsep="0" valign="top">Ergänzungsprüfung</entry></row><row><entry VJ="1" align="left" colsep="0" nameend="col2" namest="col1" valign="top">§ 20</entry><entry VJ="1" align="left" colsep="0" valign="top">Niederschrift der Prüfungskommission</entry></row><row><entry VJ="1" align="left" colsep="0" nameend="col2" namest="col1" valign="top">§ 21</entry><entry VJ="1" align="left" colsep="0" valign="top">Rücktritt von der Prüfung</entry></row><row><entry VJ="1" align="left" colsep="0" nameend="col2" namest="col1" valign="top">§ 22</entry><entry VJ="1" align="left" colsep="0" valign="top">Wiederholung der Prüfung</entry></row><row><entry VJ="1" align="left" colsep="0" nameend="col2" namest="col1" valign="top">§ 23</entry><entry VJ="1" align="left" colsep="0" valign="top">Mitteilung des Prüfungsergebnisses</entry></row><row><entry VJ="1" align="left" colsep="0" nameend="col2" namest="col1" valign="top">§ 24</entry><entry VJ="1" align="left" colsep="0" valign="top">Täuschungsversuch, Ordnungsverstöße</entry></row><row><entry VJ="1" nameend="col2" namest="col1">§ 24a</entry><entry VJ="1">Einsicht in Prüfungsakten</entry></row><row><entry VJ="1" align="left" colsep="0" nameend="col3" namest="col1" valign="top">Zweiter Teil</entry></row><row><entry VJ="1" align="left" colsep="0" valign="top"> </entry><entry VJ="1" align="left" colsep="0" nameend="col3" namest="col2" valign="top">Prüfungsverfahren nach §131l der Wirtschaftsprüferordnung</entry></row><row><entry VJ="1" align="left" colsep="0" nameend="col2" namest="col1" valign="top">§ 25</entry><entry VJ="1" align="left" colsep="0" valign="top">Antrag auf Zulassung zur Prüfung</entry></row><row><entry VJ="1" align="left" colsep="0" nameend="col2" namest="col1" valign="top">§ 26</entry><entry VJ="1" align="left" colsep="0" valign="top">Prüfungskommission, Prüfungstermine</entry></row><row><entry VJ="1" align="left" colsep="0" nameend="col2" namest="col1" valign="top">§ 27</entry><entry VJ="1" align="left" colsep="0" valign="top">Prüfungsgebiete</entry></row><row><entry VJ="1" align="left" colsep="0" nameend="col2" namest="col1" valign="top">§ 28</entry><entry VJ="1" align="left" colsep="0" valign="top">Verkürzte Prüfung; Erlass von Prüfungsleistungen</entry></row><row><entry VJ="1" align="left" colsep="0" nameend="col2" namest="col1" valign="top">§ 29</entry><entry VJ="1" align="left" colsep="0" valign="top">Schriftliche Prüfung</entry></row><row><entry VJ="1" align="left" colsep="0" nameend="col2" namest="col1" valign="top">§ 30</entry><entry VJ="1" align="left" colsep="0" valign="top">Mündliche Prüfung</entry></row><row><entry VJ="1" align="left" colsep="0" nameend="col2" namest="col1" valign="top">§ 31</entry><entry VJ="1" align="left" colsep="0" valign="top">Prüfungsergebnis</entry></row><row><entry VJ="1" align="left" colsep="0" nameend="col2" namest="col1" valign="top">§ 32</entry><entry VJ="1" align="left" colsep="0" valign="top">Rücktritt von der Prüfung</entry></row><row><entry VJ="1" align="left" colsep="0" nameend="col2" namest="col1" valign="top">§ 33</entry><entry VJ="1" align="left" colsep="0" valign="top">Wiederholung der Prüfung</entry></row><row><entry VJ="1" align="left" colsep="0" nameend="col2" namest="col1" valign="top">§ 34</entry><entry VJ="1" align="left" colsep="0" valign="top">Täuschungsversuch, Ordnungsverstöße</entry></row><row><entry VJ="1" align="left" colsep="0" nameend="col2" namest="col1" valign="top">§ 35</entry><entry VJ="1" align="left" colsep="0" valign="top">Einsicht in Prüfungsakten</entry></row></tbody></tgroup></table></P></Content></text><fussnoten/></textdaten></norm>
<norm builddate="20161007120716" doknr="BJNR170700004BJNG000100000"><metadaten><jurabk>WiPrPrüfV</jurabk><gliederungseinheit><gliederungskennzahl>010</gliederungskennzahl><gliederungsbez>Erster Teil</gliederungsbez><gliederungstitel>Prüfungsverfahren nach § 14 der
Wirtschaftsprüferordnung</gliederungstitel></gliederungseinheit></metadaten><textdaten><text format="XML"><Content><P/></Content></text></textdaten></norm>
<norm builddate="20161007120716" doknr="BJNR170700004BJNE000302118"><metadaten><jurabk>WiPrPrüfV</jurabk><enbez>§ 1</enbez><titel format="XML">Antrag auf Zulassung zur Prüfung</titel></metadaten><textdaten><text format="XML"><Content><P>(1) Der Antrag auf Zulassung zur Prüfung ist an die &quot;Prüfungsstelle für das Wirtschaftsprüfungsexamen bei der Wirtschaftsprüferkammer&quot; (Prüfungsstelle) zu richten. Dem Antrag auf Zulassung zur Prüfung sind beizufügen <DL><DT>1.</DT><DD><LA>ein tabellarischer Lebenslauf, der genaue Angaben über die Vorbildung und den beruflichen Werdegang enthält;</LA></DD><DT>2.</DT><DD><LA>Zeugnisse über Hochschulprüfungen, andere einschlägige Prüfungen und die berufliche Tätigkeit, insbesondere mit Angaben über Art und Umfang der Prüfungstätigkeit, in Urschrift oder beglaubigter Abschrift; Angaben über Art und Umfang der Prüfungstätigkeit sind nicht erforderlich, wenn der Nachweis der Prüfungstätigkeit nach § 9 Abs. 4 der Wirtschaftsprüferordnung entfällt;</LA></DD><DT>3.</DT><DD><LA>eine Erklärung darüber, ob und bei welcher Stelle bereits früher ein Antrag auf Zulassung zur Prüfung eingereicht wurde;</LA></DD><DT>4.</DT><DD><LA>ein Nachweis der Regelstudienzeit der absolvierten Hochschulausbildung;</LA></DD><DT>5.</DT><DD><LA>falls der Nachweis nicht nach § 9 Abs. 4 der Wirtschaftsprüferordnung entfällt, eine Bescheinigung über die Prüfungstätigkeit nach § 9 Abs. 2 der Wirtschaftsprüferordnung;</LA></DD><DT>6.</DT><DD><LA>(weggefallen)</LA></DD><DT>7.</DT><DD><LA>(weggefallen)</LA></DD><DT>8.</DT><DD><LA>gegebenenfalls eine Erklärung darüber, ob die Prüfung in verkürzter Form (§ 6) abgelegt werden soll.</LA></DD></DL></P><P>(2) Die Bescheinigung gemäß Absatz 1 Satz 2 Nr. 5, aus der Art und Umfang der Prüfungstätigkeit, insbesondere die Teilnahme an Abschlussprüfungen und die Mitwirkung bei der Abfassung der Prüfungsberichte, hervorgeht, ist in Urschrift oder beglaubigter Abschrift beizufügen. Die Prüfungsstelle kann die Vorlage von wenigstens zwei Prüfungsberichten verlangen. Werden Prüfungsberichte verlangt, hat die zu prüfende Person zu erklären, dass sie diese selbstständig oder im Wesentlichen selbstständig angefertigt hat und Zustimmungserklärungen der Auftraggebenden und der Auftragnehmenden zur Vorlage der Berichte beizufügen; die zu prüfende Person kann die Kennzeichnung des geprüften Gegenstandes in den Berichten beseitigen. Sind die Auftraggebenden nicht die Unternehmen, auf die sich die Prüfungsberichte beziehen, so sind außerdem deren Zustimmungserklärungen beizufügen. Bei Prüfungsberichten genossenschaftlicher Prüfungsverbände sind Zustimmungserklärungen des Prüfungsverbandes und des geprüften Unternehmens beizufügen. Werden Prüfungsberichte ohne Kennzeichnung des geprüften Gegenstandes vorgelegt, so genügt es, wenn die Auftragnehmenden erklären, dass ihnen gegenüber die Zustimmung der Auftraggebenden erteilt worden ist. Die Bescheinigung hat die ausstellende Stelle genau zu bezeichnen; sie ist von dieser auszustellen. Bescheinigungen oder eidesstattliche Versicherungen von zu prüfenden Personen, die nicht in eigener Praxis tätig sind, reichen nicht aus. Gleiches gilt für den Nachweis der Tätigkeit nach § 9 Abs. 1 der Wirtschaftsprüferordnung.</P><P>(3) Der Antrag und die beigefügten Unterlagen sind von der Prüfungsstelle bis zu fünf Jahren nach Abschluss des Prüfungsverfahrens aufzubewahren. Der Antrag und die beigefügten Unterlagen können von der zu prüfenden Person, von Mitarbeitern der Prüfungsstelle und der Wirtschaftsprüferkammer sowie von den Mitgliedern der in den §§ 2, 8 und 9 genannten Kommissionen am Aufbewahrungsort (Landesgeschäftsstellen oder Prüfungsstelle) eingesehen werden.</P></Content></text><fussnoten/></textdaten></norm>
<norm builddate="20161007120716" doknr="BJNR170700004BJNE000400000"><metadaten><jurabk>WiPrPrüfV</jurabk><enbez>§ 2</enbez><titel format="parat">Prüfungskommission, Prüfungstermine</titel></metadaten><textdaten><text format="XML"><Content><P>(1) Der Prüfungskommission gehören als Mitglieder an ein Vertreter oder eine Vertreterin der für die Wirtschaft zuständigen oder einer anderen obersten Landesbehörde (oberste Landesbehörde) als vorsitzendes Mitglied, ein Hochschullehrer oder eine Hochschullehrerin der Betriebswirtschaftslehre, ein Mitglied mit der Befähigung zum Richteramt, ein Vertreter oder eine Vertreterin der Finanzverwaltung, ein Vertreter oder eine Vertreterin der Wirtschaft und zwei Wirtschaftsprüfer oder Wirtschaftsprüferinnen. An der verkürzten Prüfung (§ 6), bei der die Prüfung im Steuerrecht entfällt, nimmt die die Finanzverwaltung vertretende Person, an der verkürzten Prüfung, bei der die Prüfung in Angewandter Betriebswirtschaftslehre und Volkswirtschaftslehre entfällt, nimmt der Hochschullehrer oder die Hochschullehrerin der Betriebswirtschaftslehre und an der verkürzten Prüfung, bei der die Prüfung im Wirtschaftsrecht entfällt, nimmt ein zusätzliches Mitglied mit der Befähigung zum Richteramt nicht teil; ein Mitglied der Kommission muss die Befähigung zum Richteramt haben.</P><P>(2) Die Kommission entscheidet mit Stimmenmehrheit. Bei Stimmengleichheit entscheidet die Stimme der vorsitzenden Person.</P><P>(3) Die Mitglieder der Prüfungskommission haben über die ihnen bei ihrer Tätigkeit bekannt gewordenen Tatsachen Verschwiegenheit zu bewahren. Mitglieder, die keine Amtsträger sind, sind bei ihrer erstmaligen Berufung zur gewissenhaften Erfüllung ihrer Obliegenheiten zu verpflichten.</P><P>(4) Die Mitglieder der Prüfungskommission sind in ihrer Prüfungstätigkeit unabhängig.</P><P>(5) Die Prüfungsstelle führt den Geschäftsbetrieb der Prüfungskommission, bestimmt die Themen für den Vortrag in der mündlichen Prüfung auf Vorschlag eines Mitglieds der Prüfungskommission, entscheidet, welches Mitglied der Prüfungskommission in welcher Prüfung tätig werden soll und trifft alle Entscheidungen, soweit nicht die Aufgaben-, die Prüfungs- oder die Widerspruchskommission zuständig sind. Sie kann zur Bewertung der Aufsichtsarbeiten auch Mitglieder der Prüfungskommission bestimmen, die nicht an der mündlichen Prüfung teilnehmen.</P><P>(6) Die Prüfungskommission kann außerhalb der mündlichen Prüfung Entscheidungen auch im schriftlichen Verfahren treffen.</P><P>(7) Es sollen mindestens zwei bundesweite Prüfungstermine im Kalenderjahr angeboten werden.</P></Content>      </text></textdaten></norm>
<norm builddate="20161007120716" doknr="BJNR170700004BJNE000503118"><metadaten><jurabk>WiPrPrüfV</jurabk><enbez>§ 3</enbez><titel format="XML">Berufung der Mitglieder der Prüfungskommission</titel></metadaten><textdaten><text format="XML"><Content><P>(1) Die Mitglieder der Prüfungskommission werden auf Vorschlag des Vorstandes der Wirtschaftsprüferkammer, welcher der Zustimmung des Bundesministeriums für Wirtschaft und Energie bedarf, vom Beirat der Wirtschaftsprüferkammer in der Regel für die Dauer von fünf Jahren berufen; die oberste Landesbehörden vertretenden Personen sind vom Beirat nach Benennung durch die obersten Landesbehörden, die untereinander abstimmen können, welche Personen welchen Landes jeweils benannt werden, zu bestellen. Mitglieder der Prüfungskommission sind in ausreichender Zahl zu berufen. Die Berufung kann aus wichtigem Grund zurückgenommen werden.</P><P>(2) Die die Finanzverwaltung vertretenden Personen sind dem Vorstand von den obersten Landesbehörden für Finanzen vorzuschlagen.</P><P>(3) Vorschläge für die die Wirtschaft vertretenden Personen sind dem Vorstand auf Anforderung vom Deutschen Industrie- und Handelskammertag einzureichen.</P><P>(4) Der Vorstand kann verlangen, dass wiederholt Vorschläge eingereicht werden. Er ist an die nach Absatz 3 eingereichten Vorschläge nicht gebunden.</P></Content></text><fussnoten/></textdaten></norm>
<norm builddate="20161007120716" doknr="BJNR170700004BJNE000602118"><metadaten><jurabk>WiPrPrüfV</jurabk><enbez>§ 4</enbez><titel format="XML">Prüfungsgebiete</titel></metadaten><textdaten><text format="XML"><Content><P>(1) Prüfungsgebiete sind <DL Font="normal" Type="arabic"><DT>1.</DT><DD Font="normal"><LA Size="normal">Wirtschaftliches Prüfungswesen, Unternehmensbewertung und Berufsrecht,</LA></DD><DT>2.</DT><DD Font="normal"><LA Size="normal">Angewandte Betriebswirtschaftslehre, Volkswirtschaftslehre,</LA></DD><DT>3.</DT><DD Font="normal"><LA Size="normal">Wirtschaftsrecht und</LA></DD><DT>4.</DT><DD Font="normal"><LA Size="normal">Steuerrecht.</LA></DD></DL></P><P>(2) Das Prüfungsgebiet Wirtschaftliches Prüfungswesen, Unternehmensbewertung und Berufsrecht umfasst: <DL Font="normal" Type="arabic"><DT>1.</DT><DD Font="normal"><LA Size="normal">Rechnungslegung <DL Font="normal" Type="alpha"><DT>a)</DT><DD Font="normal"><LA Size="normal">Buchführung, Jahresabschluss und Lagebericht,</LA></DD><DT>b)</DT><DD Font="normal"><LA Size="normal">Konzernabschluss und Konzernlagebericht, Bericht über die Beziehungen zu verbundenen Unternehmen,</LA></DD><DT>c)</DT><DD Font="normal"><LA Size="normal">international anerkannte Rechnungslegungsgrundsätze,</LA></DD><DT>d)</DT><DD Font="normal"><LA Size="normal">Rechnungslegung in besonderen Fällen,</LA></DD><DT>e)</DT><DD Font="normal"><LA Size="normal">Jahresabschlussanalyse;</LA></DD></DL></LA></DD><DT>2.</DT><DD Font="normal"><LA Size="normal">Prüfung <DL Font="normal" Type="alpha"><DT>a)</DT><DD Font="normal"><LA Size="normal">Prüfung der Rechnungslegung: rechtliche Vorschriften und Prüfungsstandards, insbesondere Prüfungsgegenstand und Prüfungsauftrag, Prüfungsansatz und Prüfungsdurchführung, Bestätigungsvermerk, Prüfungsbericht und Bescheinigungen, andere Reporting-Aufträge,</LA></DD><DT>b)</DT><DD Font="normal"><LA Size="normal">sonstige gesetzlich vorgeschriebene Prüfungen, insbesondere aktienrechtliche Sonderprüfungen, Prüfung von Risikofrüherkennungssystemen, Geschäftsführungsprüfungen,</LA></DD><DT>c)</DT><DD Font="normal"><LA Size="normal">andere betriebswirtschaftliche Prüfungen, insbesondere Due-Diligence-Prüfungen, Kreditwürdigkeitsprüfungen, Unterschlagungsprüfungen, Wirtschaftlichkeitsprüfungen, Prüfung von Sanierungskonzepten;</LA></DD></DL></LA></DD><DT>3.</DT><DD Font="normal"><LA Size="normal">Grundzüge und Prüfung der Informationstechnologie;</LA></DD><DT>4.</DT><DD Font="normal"><LA Size="normal">Bewertung von Unternehmen und Unternehmensanteilen;</LA></DD><DT>5.</DT><DD Font="normal"><LA Size="normal">Berufsrecht, insbesondere Organisation des Berufs, Berufsaufsicht, Berufsgrundsätze und Unabhängigkeit.</LA></DD></DL></P><P>(3) Das Prüfungsgebiet Angewandte Betriebswirtschaftslehre, Volkswirtschaftslehre umfasst: <DL Font="normal" Type="arabic"><DT>1.</DT><DD Font="normal"><LA Size="normal">Angewandte Betriebswirtschaftslehre <DL Font="normal" Type="alpha"><DT>a)</DT><DD Font="normal"><LA Size="normal">Kosten- und Leistungsrechnung,</LA></DD><DT>b)</DT><DD Font="normal"><LA Size="normal">Planungs- und Kontrollinstrumente,</LA></DD><DT>c)</DT><DD Font="normal"><LA Size="normal">Unternehmensführung und Unternehmensorganisation,</LA></DD><DT>d)</DT><DD Font="normal"><LA Size="normal">Unternehmensfinanzierung sowie Investitionsrechnung,</LA></DD></DL>einschließlich methodischer Problemstellungen der externen Rechnungslegung, der Corporate Governance und der Unternehmensbewertung;</LA></DD><DT>2.</DT><DD Font="normal"><LA Size="normal">Volkswirtschaftslehre <DL Font="normal" Type="alpha"><DT>a)</DT><DD Font="normal"><LA Size="normal">Grundzüge der Volkswirtschaftslehre und Volkswirtschaftspolitik,</LA></DD><DT>b)</DT><DD Font="normal"><LA Size="normal">Grundzüge der Finanzwissenschaft;</LA></DD></DL></LA></DD></DL>die Nummern 1 und 2 umfassen Grundkenntnisse anwendungsorientierter Mathematik und Statistik.</P><P>(4) Das Prüfungsgebiet Wirtschaftsrecht umfasst: <DL Font="normal" Type="arabic"><DT>1.</DT><DD Font="normal"><LA Size="normal">Grundzüge des Bürgerlichen Rechts einschließlich Grundzüge des Arbeitsrechts und Grundzüge des internationalen Privatrechts, insbesondere Recht der Schuldverhältnisse und Sachenrecht;</LA></DD><DT>2.</DT><DD Font="normal"><LA Size="normal">Handelsrecht, insbesondere Handelsstand und -geschäfte einschließlich internationalem Kaufrecht;</LA></DD><DT>3.</DT><DD Font="normal"><LA Size="normal">Gesellschaftsrecht (Personengesellschaften und Kapitalgesellschaften, Recht der verbundenen Unternehmen), Corporate Governance und Grundzüge des Kapitalmarktrechts;</LA></DD><DT>4.</DT><DD Font="normal"><LA Size="normal">Umwandlungsrecht;</LA></DD><DT>5.</DT><DD Font="normal"><LA Size="normal">Grundzüge des Insolvenzrechts;</LA></DD><DT>6.</DT><DD Font="normal"><LA Size="normal">Grundzüge des Europarechts.</LA></DD></DL></P><P>(5) Das Prüfungsgebiet Steuerrecht umfasst: <DL Font="normal" Type="arabic"><DT>1.</DT><DD Font="normal"><LA Size="normal">Abgabenordnung und Nebengesetze, Finanzgerichtsordnung;</LA></DD><DT>2.</DT><DD Font="normal"><LA Size="normal">Recht der Steuerarten, insbesondere <DL Font="normal" Type="alpha"><DT>a)</DT><DD Font="normal"><LA Size="normal">Einkommen-, Körperschaft- und Gewerbesteuer,</LA></DD><DT>b)</DT><DD Font="normal"><LA Size="normal">Bewertungsgesetz, Erbschaftsteuer, Grundsteuer,</LA></DD><DT>c)</DT><DD Font="normal"><LA Size="normal">Umsatzsteuer, Grunderwerbsteuer,</LA></DD><DT>d)</DT><DD Font="normal"><LA Size="normal">Umwandlungssteuerrecht;</LA></DD></DL></LA></DD><DT>3.</DT><DD Font="normal"><LA Size="normal">Grundzüge des Internationalen Steuerrechts.</LA></DD></DL></P></Content></text><fussnoten/></textdaten></norm>
<norm builddate="20161007120716" doknr="BJNR170700004BJNE003900118"><metadaten><jurabk>WiPrPrüfV</jurabk><enbez>§ 4a</enbez><titel format="XML">Prüfungsgebiete der verkürzten Prüfung nach § 13a der Wirtschaftsprüferordnung</titel></metadaten><textdaten><text format="XML"><Content><P>(1) Prüfungsgebiete der verkürzten Prüfung nach § 13a der Wirtschaftsprüferordnung sind <DL Type="arabic"><DT>1.</DT><DD Font="normal"><LA>Wirtschaftliches Prüfungswesen und Unternehmensbewertung,</LA></DD><DT>2.</DT><DD Font="normal"><LA>Wirtschaftsrecht und</LA></DD><DT>3.</DT><DD Font="normal"><LA>Steuerrecht.</LA></DD></DL></P><P>(2) Das Prüfungsgebiet Wirtschaftliches Prüfungswesen und Unternehmensbewertung umfasst: <DL Type="arabic"><DT>1.</DT><DD Font="normal"><LA>Rechnungslegung <DL Type="alpha"><DT>a)</DT><DD Font="normal"><LA>Konzernabschluss und Konzernlagebericht, Bericht über die Beziehungen zu verbundenen Unternehmen,</LA></DD><DT>b)</DT><DD Font="normal"><LA>international anerkannte Rechnungslegungsgrundsätze,</LA></DD><DT>c)</DT><DD Font="normal"><LA>Rechnungslegung in besonderen Fällen;</LA></DD></DL></LA></DD><DT>2.</DT><DD Font="normal"><LA>Prüfung <DL Type="alpha"><DT>a)</DT><DD Font="normal"><LA>Prüfung der Rechnungslegung, soweit von der Pflichtprüfung des Jahresabschlusses und des Lageberichts von Gesellschaften mit beschränkter Haftung abweichend: rechtliche Vorschriften und Prüfungsstandards, insbesondere Prüfungsgegenstand und Prüfungsauftrag, Prüfungsansatz und Prüfungsdurchführung, Bestätigungsvermerk, Prüfungsbericht und Bescheinigungen, andere Reporting-Aufträge,</LA></DD><DT>b)</DT><DD Font="normal"><LA>sonstige gesetzlich vorgeschriebene Prüfungen, insbesondere aktienrechtliche Sonderprüfungen, Prüfung von Risikofrüherkennungssystemen, Geschäftsführungsprüfungen,</LA></DD><DT>c)</DT><DD Font="normal"><LA>andere betriebswirtschaftliche Prüfungen, insbesondere Due-Diligence-Prüfungen, Kreditwürdigkeitsprüfungen, Unterschlagungsprüfungen, Wirtschaftlichkeitsprüfungen, Prüfung von Sanierungskonzepten;</LA></DD></DL></LA></DD><DT>3.</DT><DD Font="normal"><LA>Bewertung von Unternehmen und Unternehmensanteilen.</LA></DD></DL></P><P>(3) Das Prüfungsgebiet Wirtschaftsrecht umfasst: <DL Type="arabic"><DT>1.</DT><DD Font="normal"><LA>Grundzüge des internationalen Privatrechts, insbesondere Recht der Schuldverhältnisse;</LA></DD><DT>2.</DT><DD Font="normal"><LA>Gesellschaftsrecht (Personengesellschaften und Kapitalgesellschaften ohne Gesellschaften mit beschränkter Haftung, Recht der verbundenen Unternehmen), Corporate Governance und Grundzüge des Kapitalmarktrechts;</LA></DD><DT>3.</DT><DD Font="normal"><LA>Umwandlungsrecht;</LA></DD><DT>4.</DT><DD Font="normal"><LA>Grundzüge des Europarechts.</LA></DD></DL></P><P>(4) Das Prüfungsgebiet Steuerrecht umfasst die Inhalte nach § 4 Absatz 5.</P><P>(5) Bei der Auswahl und der Gewichtung der Prüfungsaufgaben ist die praktische Berufsarbeit der vereidigten Buchprüfer besonders zu berücksichtigen.</P></Content></text><fussnoten/></textdaten></norm>
<norm builddate="20161007120716" doknr="BJNR170700004BJNE000700000"><metadaten><jurabk>WiPrPrüfV</jurabk><enbez>§ 5</enbez><titel format="parat">Gliederung der Prüfung</titel></metadaten><textdaten><text format="XML"><Content><P>Die Prüfung gliedert sich in eine schriftliche und eine mündliche Prüfung. Die schriftliche Prüfung besteht aus sieben unter Aufsicht anzufertigenden Arbeiten (Aufsichtsarbeiten).</P></Content></text></textdaten></norm>
<norm builddate="20161007120716" doknr="BJNR170700004BJNE000800000"><metadaten><jurabk>WiPrPrüfV</jurabk><enbez>§ 6</enbez><titel format="parat">Verkürzte Prüfung</titel></metadaten><textdaten><text format="XML"><Content><P>Abweichend von § 5 kann die Prüfung in verkürzter Form nach den §§ 8a, 13 bis 13b der Wirtschaftsprüferordnung abgelegt werden.</P></Content></text></textdaten></norm>
<norm builddate="20161007120716" doknr="BJNR170700004BJNE000902118"><metadaten><jurabk>WiPrPrüfV</jurabk><enbez>§ 7</enbez><titel format="XML">Schriftliche Prüfung</titel></metadaten><textdaten><text format="XML"><Content><P>(1) Die Aufgaben für die Aufsichtsarbeiten sind aus der Berufsarbeit der Wirtschaftsprüfer und Wirtschaftsprüferinnen zu entnehmen.</P><P>(2) Für jede Aufsichtsarbeit stehen vier bis sechs Stunden zur Verfügung. Behinderten Menschen kann die Frist verlängert werden; Hilfsmittel und die Inanspruchnahme von Hilfeleistungen Dritter, die die besonderen Verhältnisse behinderter Menschen berücksichtigen, sollen von der Prüfungsstelle zugelassen werden. Es sind zu bearbeiten <DL Font="normal" Type="arabic"><DT>1.</DT><DD Font="normal"><LA Size="normal">zwei Aufgaben aus dem Gebiet Wirtschaftliches Prüfungswesen, Unternehmensbewertung und Berufsrecht (§ 4 Absatz 2),</LA></DD><DT>2.</DT><DD Font="normal"><LA Size="normal">zwei Aufgaben aus dem Gebiet Angewandte Betriebswirtschaftslehre, Volkswirtschaftslehre (§ 4 Absatz 3),</LA></DD><DT>3.</DT><DD Font="normal"><LA Size="normal">eine Aufgabe aus dem Gebiet Wirtschaftsrecht (§ 4 Absatz 4),</LA></DD><DT>4.</DT><DD Font="normal"><LA Size="normal">zwei Aufgaben aus dem Gebiet Steuerrecht (§ 4 Absatz 5).</LA></DD></DL>Es ist jeweils eine Aufgabe an je einem Tag zu bearbeiten.</P><P>(3) Abweichend von Absatz 2 Satz 3 und § 5 Satz 2 sind bei der verkürzten Prüfung nach § 13a der Wirtschaftsprüferordnung zu bearbeiten <DL Type="arabic"><DT>1.</DT><DD Font="normal"><LA>eine Aufgabe aus dem Gebiet Wirtschaftliches Prüfungswesen und Unternehmensbewertung (§ 4a Absatz 2 Nummer 1),</LA></DD><DT>2.</DT><DD Font="normal"><LA>eine Aufgabe aus dem Gebiet Wirtschaftliches Prüfungswesen und Unternehmensbewertung (§ 4a Absatz 2 Nummer 2 und 3),</LA></DD><DT>3.</DT><DD Font="normal"><LA>eine Aufgabe aus dem Gebiet Wirtschaftsrecht (§ 4a Absatz 3),</LA></DD><DT>4.</DT><DD Font="normal"><LA>zwei Aufgaben aus dem Gebiet Steuerrecht (§ 4a Absatz 4).</LA></DD></DL>Abweichend von Absatz 2 Satz 1 stehen für jede Aufsichtsarbeit nach Nummer 1 bis 3 zwei Stunden zur Verfügung.</P></Content></text><fussnoten/></textdaten></norm>
<norm builddate="20161007120716" doknr="BJNR170700004BJNE001000000"><metadaten><jurabk>WiPrPrüfV</jurabk><enbez>§ 8</enbez><titel format="parat">Aufgabenkommission</titel></metadaten><textdaten><text format="XML"><Content><P>(1) Für das Bestimmen der Prüfungsaufgaben in der schriftlichen Prüfung und für die Entscheidung über die zugelassenen Hilfsmittel wird bei der Prüfungsstelle eine Aufgabenkommission eingerichtet. Die Kommission gibt sich bei Bedarf eine eigene Geschäftsordnung.</P><P>(2) Der Aufgabenkommission gehören als Mitglieder eine Person, die eine oberste Landesbehörde vertritt, als vorsitzendes Mitglied, die Leitung der Prüfungsstelle, eine die Wirtschaft vertretende Person, ein Mitglied mit Befähigung zum Richteramt, das auch Mitglied des wirtschaftsprüfenden Berufsstandes sein kann, zwei Hochschullehrer oder Hochschullehrerinnen für Betriebswirtschaftslehre, zwei Berufsangehörige und eine die Finanzverwaltung vertretende Person an.</P><P>(3) Die Aufgabenkommission entscheidet mit Zweidrittelmehrheit.</P><P>(4) § 2 Abs. 3 und 4 sowie § 3 gelten entsprechend, jedoch werden die Mitglieder der Aufgabenkommission in der Regel für die Dauer von drei Jahren berufen.</P></Content>   </text></textdaten></norm>
<norm builddate="20161007120716" doknr="BJNR170700004BJNE001100000"><metadaten><jurabk>WiPrPrüfV</jurabk><enbez>§ 9</enbez><titel format="parat">Widerspruchskommission</titel></metadaten><textdaten><text format="XML"><Content><P>Für Entscheidungen nach § 5 Abs. 5 der Wirtschaftsprüferordnung wird bei der Prüfungsstelle eine Widerspruchskommission eingerichtet, die personell mit der Aufgabenkommission nach § 8 Abs. 2 identisch ist. Die Kommission entscheidet mit Stimmenmehrheit; bei Stimmengleichheit entscheidet die Stimme des vorsitzenden Mitglieds. § 8 Abs. 4 gilt entsprechend.</P></Content></text></textdaten></norm>
<norm builddate="20161007120716" doknr="BJNR170700004BJNE001200000"><metadaten><jurabk>WiPrPrüfV</jurabk><enbez>§ 10</enbez><titel format="parat">Aufsichtsarbeiten</titel></metadaten><textdaten><text format="XML"><Content><P>Die Aufsicht bei den Aufsichtsarbeiten führen von der Prüfungsstelle bestimmte Personen. Über die Anfertigung der Aufsichtsarbeiten haben sie eine Niederschrift zu fertigen, in der die teilnehmenden Personen, der Zeitpunkt des Beginns und der Abgabe der Arbeiten, etwaige Ordnungsverstöße sowie alle sonstigen wesentlichen Vorkommnisse aufzunehmen sind.</P></Content></text></textdaten></norm>
<norm builddate="20161007120716" doknr="BJNR170700004BJNE001301118"><metadaten><jurabk>WiPrPrüfV</jurabk><enbez>§ 11</enbez><titel format="XML">Prüfungsnoten</titel></metadaten><textdaten><text format="XML"><Content><P>(1) Für die Bewertung der einzelnen Prüfungsleistungen werden sechs Notenstufen gebildet. Es bedeuten <BR/><BR/><table frame="none" tocentry="%yes;"><tgroup align="left" char="" charoff="50" cols="2" colsep="0" rowsep="0"><colspec colname="col1" colnum="1" colwidth="40*"/><colspec colname="col2" colnum="2" colwidth="70*"/><tbody valign="top"><row><entry VJ="1" align="left" colsep="0" valign="top">Note 1 sehr gut</entry><entry VJ="1" align="left" colsep="0" valign="top">eine hervorragende Leistung,</entry></row><row><entry VJ="1" align="left" colsep="0" valign="top">Note 2 gut</entry><entry VJ="1" align="left" colsep="0" valign="top">eine erheblich über dem Durchschnitt liegende Leistung,</entry></row><row><entry VJ="1" align="left" colsep="0" valign="top">Note 3 befriedigend</entry><entry VJ="1" align="left" colsep="0" valign="top">eine Leistung, die in jeder Hinsicht durchschnittlichen Anforderungen gerecht wird,</entry></row><row><entry VJ="1" align="left" colsep="0" valign="top">Note 4 ausreichend</entry><entry VJ="1" align="left" colsep="0" valign="top">eine Leistung, die abgesehen von einzelnen Mängeln durchschnittlichen Anforderungen entspricht,</entry></row><row><entry VJ="1" align="left" colsep="0" valign="top">Note 5 mangelhaft</entry><entry VJ="1" align="left" colsep="0" valign="top">eine an erheblichen Mängeln leidende, im Ganzen nicht mehr brauchbare Leistung,</entry></row><row><entry VJ="1" align="left" colsep="0" valign="top">Note 6 ungenügend</entry><entry VJ="1" align="left" colsep="0" valign="top">eine völlig unbrauchbare Leistung.</entry></row></tbody></tgroup></table><BR/><BR/>Die Bewertung mit halben Zwischennoten ist zulässig.</P><P>(2) Bei der Ermittlung von Gesamtnoten bedeuten <BR/><BR/><table frame="none" tocentry="%yes;"><tgroup align="left" char="" charoff="50" cols="2" colsep="0" rowsep="0"><colspec colname="col1" colnum="1" colwidth="40*"/><colspec colname="col2" colnum="2" colwidth="30*"/><tbody valign="top"><row><entry VJ="1" align="left" colsep="0" valign="top">Note 1</entry><entry VJ="1" align="left" colsep="0" valign="top">= sehr gut</entry></row><row><entry VJ="1" align="left" colsep="0" valign="top">Note 1,01 bis 2,00</entry><entry VJ="1" align="left" colsep="0" valign="top">= gut</entry></row><row><entry VJ="1" align="left" colsep="0" valign="top">Note 2,01 bis 3,00</entry><entry VJ="1" align="left" colsep="0" valign="top">= befriedigend</entry></row><row><entry VJ="1" align="left" colsep="0" valign="top">Note 3,01 bis 4,00</entry><entry VJ="1" align="left" colsep="0" valign="top">= ausreichend</entry></row><row><entry VJ="1" align="left" colsep="0" valign="top">Note 4,01 bis 5,00</entry><entry VJ="1" align="left" colsep="0" valign="top">= mangelhaft</entry></row><row><entry VJ="1" align="left" colsep="0" valign="top">Note 5,01 bis 6,00</entry><entry VJ="1" align="left" colsep="0" valign="top">= ungenügend.</entry></row></tbody></tgroup></table><BR/><BR/>Gesamtnoten errechnen sich aus der Summe der einzelnen Noten, geteilt durch deren Zahl. Das Ergebnis ist auf zwei Dezimalstellen ohne Rundung zu berechnen.</P></Content></text><fussnoten/></textdaten></norm>
<norm builddate="20161007120716" doknr="BJNR170700004BJNE001400000"><metadaten><jurabk>WiPrPrüfV</jurabk><enbez>§ 12</enbez><titel format="parat">Bewertung der Aufsichtsarbeiten</titel></metadaten><textdaten><text format="XML"><Content><P>(1) Jede Aufsichtsarbeit ist von zwei Mitgliedern der Prüfungskommission, die nicht an der mündlichen Prüfung teilnehmen müssen, selbstständig zu bewerten. Die beiden Bewertungen können gegenseitig mitgeteilt werden. Eine nicht abgegebene Arbeit ist mit der Note 6,00 zu bewerten. Die bei der mündlichen Prüfung mitwirkenden Mitglieder der Prüfungskommission haben das Recht, die Arbeit einzusehen.</P><P>(2) Weichen die Bewertungen einer Arbeit voneinander ab, so gilt der Durchschnitt der Bewertungen.</P></Content> </text></textdaten></norm>
<norm builddate="20161007120716" doknr="BJNR170700004BJNE001501118"><metadaten><jurabk>WiPrPrüfV</jurabk><enbez>§ 13</enbez><titel format="XML">Ergebnis der schriftlichen Prüfung; Ausschluss von der mündlichen Prüfung</titel></metadaten><textdaten><text format="XML"><Content><P>(1) Für die schriftliche Prüfung wird eine Gesamtnote gebildet.</P><P>(2) Wer in der schriftlichen Prüfung nicht mindestens die Gesamtnote 5,00 erhalten hat, ist von der mündlichen Prüfung ausgeschlossen. Die Prüfung ist nicht bestanden.</P><P>(3) Absatz 2 gilt entsprechend, wenn die Aufsichtsarbeiten aus dem Gebiet Wirtschaftliches Prüfungswesen, Unternehmensbewertung und Berufsrecht im Durchschnitt nicht mindestens mit der Note 5,00 bewertet sind. Abweichend davon gilt bei der verkürzten Prüfung nach § 13a der Wirtschaftsprüferordnung Absatz 2 entsprechend, wenn die Aufsichtsarbeiten aus dem Gebiet Wirtschaftliches Prüfungswesen und Unternehmensbewertung im Durchschnitt nicht mindestens mit der Note 5,00 bewertet sind.</P></Content></text><fussnoten/></textdaten></norm>
<norm builddate="20161007120716" doknr="BJNR170700004BJNE001600000"><metadaten><jurabk>WiPrPrüfV</jurabk><enbez>§ 14</enbez><titel format="parat">Vorberatung der Prüfungskommission</titel></metadaten><textdaten><text format="XML"><Content><P>Vor Beginn der mündlichen Prüfung findet eine Vorberatung der Prüfungskommission statt, zu der sämtliche Prüfungsunterlagen vorliegen.</P></Content></text></textdaten></norm>
<norm builddate="20161007120716" doknr="BJNR170700004BJNE001701118"><metadaten><jurabk>WiPrPrüfV</jurabk><enbez>§ 15</enbez><titel format="XML">Mündliche Prüfung</titel></metadaten><textdaten><text format="XML"><Content><P>(1) Die mündliche Prüfung besteht aus einem kurzen Vortrag und fünf Prüfungsabschnitten, und zwar zwei Prüfungsabschnitten aus dem Gebiet Wirtschaftliches Prüfungswesen, Unternehmensbewertung und Berufsrecht, einem Prüfungsabschnitt aus dem Gebiet Angewandte Betriebswirtschaftslehre, Volkswirtschaftslehre, einem Prüfungsabschnitt aus dem Gebiet Wirtschaftsrecht und einem Prüfungsabschnitt aus dem Gebiet Steuerrecht. Abweichend davon besteht die mündliche Prüfung bei der verkürzten Prüfung nach § 13a der Wirtschaftsprüferordnung aus einem kurzen Vortrag und vier Prüfungsabschnitten, und zwar zwei Prüfungsabschnitten aus dem Gebiet Wirtschaftliches Prüfungswesen und Unternehmensbewertung, einem Prüfungsabschnitt aus dem Gebiet Wirtschaftsrecht und einem Prüfungsabschnitt aus dem Gebiet Steuerrecht.</P><P>(2) Die mündliche Prüfung beginnt mit einem kurzen Vortrag der zu prüfenden Person über einen Gegenstand aus der Berufsarbeit der Wirtschaftsprüfer und Wirtschaftsprüferinnen, für den ihr eine halbe Stunde vorher aus jedem der in § 4 genannten Prüfungsgebiete ein Thema zur Wahl gestellt wird. Bei verkürzten Prüfungen nach den §§ 8a, 13 und 13b der Wirtschaftsprüferordnung werden drei Themen zur Wahl gestellt; umfasst die Prüfung weniger als drei Prüfungsgebiete, erhöht sich die Zahl der Themen aus dem Prüfungsgebiet nach § 4 Absatz 2 entsprechend. Die Dauer des Vortrags soll zehn Minuten nicht überschreiten. Im Anschluss daran sind aus den in § 4 genannten Prüfungsgebieten Fragen zu stellen, die mit der Berufsarbeit der Wirtschaftsprüfer und Wirtschaftsprüferinnen zusammenhängen. Bei der verkürzten Prüfung nach § 13a der Wirtschaftsprüferordnung gelten die Sätze 1 bis 4 mit der Maßgabe, dass sich die Prüfungsgebiete jeweils aus § 4a, im Fall des Satzes 2 aus § 4a Absatz 2 ergeben.</P><P>(3) Die Dauer der Prüfung soll für die einzelne zu prüfende Person zwei Stunden nicht überschreiten. Für Personen, die nach § 13a der Wirtschaftsprüferordnung die Prüfung in verkürzter Form ablegen, soll die Dauer der Prüfung für die einzelne Person eine Stunde nicht überschreiten. Bei verkürzten Prüfungen nach § 8a oder § 13b der Wirtschaftsprüferordnung bleiben die hierfür geltenden Bestimmungen der Ausführungsverordnung unberührt.</P><P>(4) Die mündliche Prüfung ist nicht öffentlich. Die Prüfungsstelle kann mit dem Wirtschaftsprüfungsexamen befassten Personen gestatten, bei der mündlichen Prüfung zuzuhören. Sie kann für technische Hilfeleistungen Beschäftigte der Wirtschaftsprüferkammer zuziehen; anstelle solcher Personen oder neben solchen Personen können auch andere Personen zugezogen werden.</P><P>(5) Zur Prüfung zugelassenen Personen sowie Personen, die mindestens vier Jahre im wirtschaftlichen Prüfungswesen tätig sind und ein berechtigtes Interesse glaubhaft machen, kann auf Antrag gestattet werden, einmal bei der mündlichen Prüfung zuzuhören.</P></Content></text><fussnoten/></textdaten></norm>
<norm builddate="20161007120716" doknr="BJNR170700004BJNE001801118"><metadaten><jurabk>WiPrPrüfV</jurabk><enbez>§ 16</enbez><titel format="XML">Bewertung der mündlichen Prüfung</titel></metadaten><textdaten><text format="XML"><Content><P>(1) In der mündlichen Prüfung werden der kurze Vortrag und die einzelnen Prüfungsabschnitte jeweils gesondert bewertet.</P><P>(2) Die Noten werden auf Vorschlag der jeweils prüfenden Person von der Prüfungskommission festgesetzt.</P><P>(3) Für die mündliche Prüfung wird eine Gesamtnote gebildet.</P></Content></text><fussnoten/></textdaten></norm>
<norm builddate="20161007120716" doknr="BJNR170700004BJNE001900000"><metadaten><jurabk>WiPrPrüfV</jurabk><enbez>§ 17</enbez><titel format="parat">Prüfungsgesamtnote</titel></metadaten><textdaten><text format="XML"><Content><P>Aus der Gesamtnote der schriftlichen Prüfung und der Gesamtnote der mündlichen Prüfung ist eine Prüfungsgesamtnote zu bilden. Sie wird errechnet, indem die Gesamtnote der schriftlichen Prüfung mit 6, die Gesamtnote der mündlichen Prüfung mit 4 vervielfältigt und sodann die Summe durch 10 geteilt wird.</P></Content></text></textdaten></norm>
<norm builddate="20161007120716" doknr="BJNR170700004BJNE002001118"><metadaten><jurabk>WiPrPrüfV</jurabk><enbez>§ 18</enbez><titel format="XML">Prüfungsergebnis</titel></metadaten><textdaten><text format="XML"><Content><P>(1) Die Prüfungskommission entscheidet im Anschluss an die mündliche Prüfung, ob die Prüfung bestanden, nicht bestanden oder ob und in welchem Umfang eine Ergänzungsprüfung abzulegen ist. Die Prüfung ist bestanden, wenn auf jedem Prüfungsgebiet eine unter entsprechender Anwendung des § 17 Satz 2 mindestens mit der Note 4,00 bewertete Leistung erbracht wurde. Dabei ist bei der Ermittlung des Ergebnisses der mündlichen Prüfung auf den einzelnen Prüfungsgebieten der kurze Vortrag (§ 15 Abs. 1) unter entsprechender Anwendung des § 16 Abs. 3 dem Prüfungsgebiet zuzurechnen, dem er entnommen ist. Abweichend von Absatz 1 Satz 2 ist die verkürzte Prüfung nach § 13a der Wirtschaftsprüferordnung bestanden, wenn die geprüfte Person eine Prüfungsgesamtnote von mindestens 4,00 erzielt hat.</P><P>(2) Die Entscheidung der Prüfungskommission ist der geprüften Person im Anschluss an die mündliche Prüfung bekannt zu geben. Sie erhält bei bestandener Prüfung hierüber eine Bescheinigung.</P><P>(3) Die Ablegung der Prüfung berechtigt nicht zur Führung einer Bezeichnung, die auf das Bestehen der Prüfung Bezug nimmt.</P></Content></text><fussnoten/></textdaten></norm>
<norm builddate="20161007120716" doknr="BJNR170700004BJNE002101118"><metadaten><jurabk>WiPrPrüfV</jurabk><enbez>§ 19</enbez><titel format="XML">Ergänzungsprüfung</titel></metadaten><textdaten><text format="XML"><Content><P>(1) Hat die geprüfte Person eine Prüfungsgesamtnote von mindestens 4,00 erzielt, aber nach § 18 Abs. 1 Satz 2 und 3 auf einem oder mehreren Prüfungsgebieten eine mit geringer als 4,00 bewertete Leistung erbracht, so ist eine Ergänzungsprüfung auf diesen Gebieten abzulegen. Sie gliedert sich in eine schriftliche und eine mündliche Prüfung ohne kurzen Vortrag. Satz 1 ist auf die verkürzte Prüfung nach § 13a der Wirtschaftsprüferordnung nicht anzuwenden.</P><P>(2) Hat die geprüfte Person eine Prüfungsgesamtnote von mindestens 4,00 nicht erzielt, aber nach § 18 Abs. 1 Satz 2 und 3 nur auf einem Prüfungsgebiet bei sonst mit mindestens 4,00 bewerteten Leistungen eine mit geringer als 4,00 bewertete Leistung erbracht, so ist eine Ergänzungsprüfung auf diesem Gebiet abzulegen. Sie gliedert sich in eine schriftliche und eine mündliche Prüfung ohne kurzen Vortrag. Satz 1 ist auf die verkürzte Prüfung nach § 13a der Wirtschaftsprüferordnung nicht anzuwenden. Das Prüfungsergebnis in der schriftlichen und mündlichen Ergänzungsprüfung ersetzt das ursprüngliche Prüfungsergebnis.</P><P>(3) Die geprüfte Person kann sich nur innerhalb eines Jahres nach dem Tag der Mitteilung des Prüfungsergebnisses zur Ablegung der Ergänzungsprüfung melden; über Ausnahmen entscheidet die Prüfungsstelle.</P><P>(4) Die geprüfte Person hat auf jedem Gebiet, auf dem sie eine Ergänzungsprüfung abzulegen hat, eine mindestens mit 4,00 zu bewertende Leistung zu erbringen; andernfalls hat sie die gesamte Prüfung nicht bestanden.</P><P>(5) Umfasst die Prüfung nur das Prüfungsgebiet nach § 4 Absatz 2, finden die Absätze 1 und 2 keine Anwendung.</P></Content></text><fussnoten/></textdaten></norm>
<norm builddate="20161007120716" doknr="BJNR170700004BJNE002200000"><metadaten><jurabk>WiPrPrüfV</jurabk><enbez>§ 20</enbez><titel format="parat">Niederschrift der Prüfungskommission</titel></metadaten><textdaten><text format="XML"><Content><P>(1) Über den Hergang der mündlichen Prüfung ist eine Niederschrift aufzunehmen, in der festgestellt werden <DL Font="normal" Type="arabic"><DT>1.</DT><DD Font="normal"><LA Size="normal">die Besetzung der Prüfungskommission;</LA></DD> <DT>2.</DT><DD Font="normal"><LA Size="normal">die Bewertung der schriftlichen Arbeiten und die Gesamtnote der schriftlichen Prüfung;</LA></DD> <DT>3.</DT><DD Font="normal"><LA Size="normal">die Einzelergebnisse und die Gesamtnote der mündlichen Prüfung;</LA></DD> <DT>4.</DT><DD Font="normal"><LA Size="normal">die Prüfungsgesamtnote;</LA></DD> <DT>5.</DT><DD Font="normal"><LA Size="normal">die Entscheidung der Prüfungskommission über das Ergebnis der Prüfung.</LA></DD> </DL> </P><P>(2) Die Niederschrift ist von der vorsitzenden Person der Prüfungskommission zu unterschreiben.</P></Content></text></textdaten></norm>
<norm builddate="20161007120716" doknr="BJNR170700004BJNE002301118"><metadaten><jurabk>WiPrPrüfV</jurabk><enbez>§ 21</enbez><titel format="XML">Rücktritt von der Prüfung</titel></metadaten><textdaten><text format="XML"><Content><P>(1) Tritt die zu prüfende Person von der Prüfung zurück, so gilt die gesamte Prüfung als nicht bestanden. Als Rücktritt gilt es, wenn sie an einer Aufsichtsarbeit nicht teilnimmt oder sich der mündlichen Prüfung oder Teilen derselben nicht unterzieht oder sich nicht innerhalb der Frist des § 19 Abs. 3 zur Ablegung der Ergänzungsprüfung meldet.</P><P>(2) Als Rücktritt gilt es nicht, wenn die zu prüfende Person an einer Aufsichtsarbeit nicht teilnimmt oder sich der mündlichen Prüfung oder Teilen derselben nicht unterzieht und hierfür ein triftiger Grund vorliegt. Der Grund muss der Prüfungsstelle unverzüglich schriftlich oder elektronisch mitgeteilt und nachgewiesen werden. Die Prüfungsstelle entscheidet, ob ein Grund als triftig anzusehen ist und ob der Nachweis rechtzeitig erbracht ist. Bei behaupteter Krankheit kann die Vorlage eines amtsärztlichen Zeugnisses verlangt werden.</P><P>(3) Im Falle des Absatzes 2 ist die zu prüfende Person zu einem späteren Prüfungstermin zur Ablegung der noch nicht erledigten Teile der schriftlichen Prüfung oder der noch nicht erledigten mündlichen Prüfung erneut zu laden.</P></Content></text><fussnoten/></textdaten></norm>
<norm builddate="20161007120716" doknr="BJNR170700004BJNE002403118"><metadaten><jurabk>WiPrPrüfV</jurabk><enbez>§ 22</enbez><titel format="XML">Wiederholung der Prüfung</titel></metadaten><textdaten><text format="XML"><Content><P>(1) Die Prüfung kann zweimal wiederholt werden; nicht bestandene Prüfungsversuche einer bis zum 31. Dezember 2009 abgelegten verkürzten Prüfung nach § 13a der Wirtschaftsprüferordnung in der Fassung vom 27. Dezember 2004 bleiben unberücksichtigt. Für die Wiederholung der Prüfung ist eine erneute Zulassung erforderlich.</P><P>(2) Wird der Antrag auf erneute Zulassung gestellt, sind nur die in § 1 Abs. 1 Satz 2 Nr. 1, 3 und 8 genannten Unterlagen und Erklärungen beizufügen; dies gilt nicht für Anträge nach dem 31. Dezember 2003, wenn die Zulassung zur vorhergehenden Prüfung bereits vor dem 1. Januar 2004 erfolgt ist.</P></Content></text><fussnoten/></textdaten></norm>
<norm builddate="20161007120716" doknr="BJNR170700004BJNE002500000"><metadaten><jurabk>WiPrPrüfV</jurabk><enbez>§ 23</enbez><titel format="parat">Mitteilung des Prüfungsergebnisses</titel></metadaten><textdaten><text format="XML"><Content><P>Die Prüfungsstelle teilt der geprüften Person das Prüfungsergebnis mit, auf Wunsch mit Angabe der Prüfungsgesamtnote. Bei Angabe der Prüfungsgesamtnote ist gegebenenfalls das Ablegen einer Ergänzungsprüfung ohne Angabe des ursprünglichen Prüfungsergebnisses zu erwähnen.</P></Content></text></textdaten></norm>
<norm builddate="20161007120716" doknr="BJNR170700004BJNE002600000"><metadaten><jurabk>WiPrPrüfV</jurabk><enbez>§ 24</enbez><titel format="parat">Täuschungsversuch, Ordnungsverstöße</titel></metadaten><textdaten><text format="XML"><Content><P>(1) Unternimmt es eine zu prüfende Person, das Ergebnis einer schriftlichen Arbeit durch Täuschung oder Benutzung nicht zugelassener Hilfsmittel zu beeinflussen, so kann die Prüfungskommission die Arbeit mit der Note 6,00 bewerten oder in schweren Fällen diese Person von der Prüfung ausschließen. Satz 1 gilt entsprechend für die mündliche Prüfung.</P><P>(2) Eine zu prüfende Person kann auch bei sonstigen erheblichen Verstößen gegen die Ordnung von der Prüfung ausgeschlossen werden.</P><P>(3) Im Falle des Ausschlusses gilt die Prüfung als nicht bestanden.</P><P>(4) Wird nachträglich festgestellt, dass die Voraussetzungen des Absatzes 1 vorlagen, so kann die Prüfungskommission die ergangene Prüfungsentscheidung widerrufen und aussprechen, dass die Prüfung nicht bestanden ist. Der Widerruf ist ausgeschlossen, wenn seit der Beendigung der Prüfung mehr als drei Jahre vergangen sind.</P></Content>   </text></textdaten></norm>
<norm builddate="20161007120716" doknr="BJNR170700004BJNE004000118"><metadaten><jurabk>WiPrPrüfV</jurabk><enbez>§ 24a</enbez><titel format="XML">Einsicht in Prüfungsakten</titel></metadaten><textdaten><text format="XML"><Content><P>Die geprüfte Person kann nach Bekanntgabe des Ergebnisses der Prüfung die Prüfungsakten persönlich einsehen.</P></Content></text><fussnoten/></textdaten></norm>
<norm builddate="20161007120716" doknr="BJNR170700004BJNG000200000"><metadaten><jurabk>WiPrPrüfV</jurabk><gliederungseinheit><gliederungskennzahl>020</gliederungskennzahl><gliederungsbez>Zweiter Teil</gliederungsbez><gliederungstitel>Prüfungsverfahren nach § 131l der
Wirtschaftsprüferordnung</gliederungstitel></gliederungseinheit></metadaten><textdaten><text format="XML"><Content><P/></Content></text></textdaten></norm>
<norm builddate="20161007120716" doknr="BJNR170700004BJNE002702118"><metadaten><jurabk>WiPrPrüfV</jurabk><enbez>§ 25</enbez><titel format="XML">Antrag auf Zulassung zur Prüfung</titel></metadaten><textdaten><text format="XML"><Content><P>(1) Der Antrag auf Zulassung zur Eignungsprüfung ist an die &quot;Prüfungsstelle für das Wirtschaftsprüfungsexamen bei der Wirtschaftsprüferkammer&quot; (Prüfungsstelle) zu richten.</P><P>(2) Dem Antrag auf Zulassung zur Prüfung sind beizufügen: <DL><DT>1.</DT><DD><LA>ein tabellarischer Lebenslauf, der genaue Angaben über die Vorbildung und den beruflichen Werdegang enthält;</LA></DD><DT>2.</DT><DD Font="normal"><LA>eine Bescheinigung der zuständigen Behörde eines Staates gemäß § 131g Absatz 1 der Wirtschaftsprüferordnung, durch die nachgewiesen wird, dass die zu prüfende Person Abschlussprüfer ist;</LA></DD><DT>3.</DT><DD><LA>(weggefallen)</LA></DD><DT>4.</DT><DD><LA>eine Erklärung über das Wahlfach für die mündliche Prüfung;</LA></DD><DT>5.</DT><DD><LA>eine Erklärung, ob und bei welcher Stelle im Geltungsbereich dieser Verordnung bereits früher ein Antrag auf Zulassung zur Prüfung eingereicht wurde;</LA></DD><DT>6.</DT><DD><LA>Unterlagen, aus denen sich die Staatsangehörigkeit ergibt;</LA></DD><DT>7.</DT><DD><LA>gegebenenfalls eine Erklärung, dass die Prüfung in verkürzter Form (§ 28 Abs. 1) abgelegt werden soll;</LA></DD><DT>8.</DT><DD><LA>gegebenenfalls ein Antrag auf Erlass von Prüfungsleistungen nach § 28 Abs. 2 und 3.</LA></DD></DL></P><P>(3) Der Antrag und die beizufügenden Unterlagen sind, soweit sie von der zu prüfenden Person stammen, in deutscher Sprache einzureichen; sonstige Unterlagen sind mit einer beglaubigten Übersetzung durch einen hierzu ermächtigten Übersetzer oder durch eine hierzu ermächtigte Übersetzerin im Geltungsbereich dieser Verordnung vorzulegen, soweit sie nicht in deutscher Sprache abgefasst sind. Prüfungssprache ist Deutsch. § 1 Abs. 3 gilt entsprechend.</P></Content></text><fussnoten/></textdaten></norm>
<norm builddate="20161007120716" doknr="BJNR170700004BJNE002801118"><metadaten><jurabk>WiPrPrüfV</jurabk><enbez>§ 26</enbez><titel format="XML">Prüfungskommission, Prüfungstermine</titel></metadaten><textdaten><text format="XML"><Content><P>(1) Der Prüfungskommission gehören als Mitglieder an eine eine oberste Landesbehörde vertretende Person als vorsitzendes Mitglied, eine die Finanzverwaltung vertretende Person, eine weitere Person mit der Befähigung zum Richteramt und zwei Wirtschaftsprüfer oder Wirtschaftsprüferinnen. An der verkürzten Prüfung (§ 28 Abs. 1), bei der die Prüfung im Steuerrecht entfällt, nimmt die die Finanzverwaltung vertretende Person nicht teil.</P><P>(2) § 2 Absatz 2 bis 7 und § 3 Abs. 1, 2 und 4 gelten entsprechend.</P></Content></text><fussnoten/></textdaten></norm>
<norm builddate="20161007120716" doknr="BJNR170700004BJNE002901118"><metadaten><jurabk>WiPrPrüfV</jurabk><enbez>§ 27</enbez><titel format="XML">Prüfungsgebiete</titel></metadaten><textdaten><text format="XML"><Content><P>(1) In der Eignungsprüfung sind Prüfungsgebiete der schriftlichen Prüfung <DL Font="normal" Type="arabic"><DT>1.</DT><DD Font="normal"><LA Size="normal">Wirtschaftsrecht <DL Font="normal" Type="alpha"><DT>a)</DT><DD Font="normal"><LA Size="normal">Grundzüge des Bürgerlichen Rechts einschließlich Grundzüge des Arbeitsrechts, soweit es für die praktische Berufsarbeit des Wirtschaftsprüfers von Bedeutung ist, mit Ausnahme des Familienrechts und des Erbrechts,</LA></DD><DT>b)</DT><DD Font="normal"><LA Size="normal">Grundzüge des Handelsrechts, insbesondere Handelsstand und -geschäfte,</LA></DD><DT>c)</DT><DD Font="normal"><LA Size="normal">Gesellschaftsrecht (Personengesellschaften und Kapitalgesellschaften, Recht der verbundenen Unternehmen) und Corporate Governance,</LA></DD><DT>d)</DT><DD Font="normal"><LA Size="normal">Umwandlungsrecht;</LA></DD></DL></LA></DD><DT>2.</DT><DD Font="normal"><LA Size="normal">Steuerrecht I <DL Font="normal" Type="alpha"><DT>a)</DT><DD Font="normal"><LA Size="normal">Abgabenordnung und Nebengesetze, Finanzgerichtsordnung,</LA></DD><DT>b)</DT><DD Font="normal"><LA Size="normal">Einkommen- und Körperschaftsteuer,</LA></DD><DT>c)</DT><DD Font="normal"><LA Size="normal">Bewertungsgesetz,</LA></DD><DT>d)</DT><DD Font="normal"><LA Size="normal">Grundzüge des Internationalen Steuerrechts,</LA></DD><DT>e)</DT><DD Font="normal"><LA Size="normal">Umwandlungssteuerrecht.</LA></DD></DL></LA></DD></DL></P><P>(2) In der Eignungsprüfung sind Prüfungsgebiete der mündlichen Prüfung <DL Font="normal" Type="arabic"><DT>1.</DT><DD Font="normal"><LA Size="normal">Wirtschaftliches Prüfungswesen <DL Font="normal" Type="alpha"><DT>a)</DT><DD Font="normal"><LA Size="normal">rechtliche Vorschriften über Rechnungslegung: Buchführung, Jahresabschluss und Lagebericht,</LA></DD><DT>b)</DT><DD Font="normal"><LA Size="normal">rechtliche Vorschriften über die Pflichtprüfung des Jahresabschlusses und des Lageberichts von Kapitalgesellschaften und Personenhandelsgesellschaften im Sinne des § 264a des Handelsgesetzbuchs einschließlich des Konzernabschlusses und des Konzernlageberichts;</LA></DD></DL></LA></DD><DT>2.</DT><DD Font="normal"><LA Size="normal">Berufsrecht der Wirtschaftsprüfer, insbesondere Organisation des Berufs, Berufsaufsicht, Berufsgrundsätze und Unabhängigkeit;</LA></DD><DT>3.</DT><DD Font="normal"><LA Size="normal">ein vom Bewerber zu bestimmendes Wahlfach; als Wahlfach können gewählt werden die Prüfungsgebiete <DL Font="normal" Type="alpha"><DT>a)</DT><DD Font="normal"><LA Size="normal">Steuerrecht II (Erbschaftsteuer, Gewerbesteuer, Grundsteuer),</LA></DD><DT>b)</DT><DD Font="normal"><LA Size="normal">Insolvenzrecht,</LA></DD><DT>c)</DT><DD Font="normal"><LA Size="normal">Grundzüge des Kapitalmarktrechts.</LA></DD></DL></LA></DD></DL>Genügt eine Aufsichtsarbeit nicht den Anforderungen, so ist zusätzlich das Prüfungsgebiet, aus dem diese Arbeit entnommen wurde, Gegenstand der mündlichen Prüfung.</P><P>(3) Die Prüfungsgebiete nach Absatz 1 Nummer 1 Buchstabe c sowie Absatz 2 Satz 1 Nummer 1 sind nur insoweit Prüfungsgegenstand, als sie nicht durch Richtlinien des Rates angeglichen worden sind oder das Recht der Bundesrepublik Deutschland, insbesondere auf Grund von in den Richtlinien eingeräumten Wahlmöglichkeiten, Besonderheiten enthält.</P></Content></text><fussnoten/></textdaten></norm>
<norm builddate="20161007120716" doknr="BJNR170700004BJNE003000000"><metadaten><jurabk>WiPrPrüfV</jurabk><enbez>§ 28</enbez><titel format="parat">Verkürzte Prüfung; Erlass von Prüfungsleistungen</titel></metadaten><textdaten><text format="XML"><Content><P>(1) Für die verkürzte Prüfung gilt § 6 entsprechend.</P><P>(2) Die Prüfungsstelle erlässt auf Antrag einzelne Prüfungsleistungen, wenn die zu prüfende Person durch ein Prüfungszeugnis nachweist, dass sie in ihrer bisherigen Ausbildung in einem Prüfungsgebiet die für die Ausübung des Berufs in der Bundesrepublik Deutschland erforderlichen Kenntnisse in diesem Prüfungsgebiet erworben hat.</P><P>(3) Die Prüfungsstelle erlässt auf Antrag einzelne Prüfungsleistungen, wenn die zu prüfende Person nachweist, dass sie durch Berufserfahrung einen wesentlichen Teil der Kenntnisse erworben hat, die durch die erlassenen Prüfungsleistungen gefordert werden. Zur Überprüfung der im Rahmen der bisherigen beruflichen Tätigkeit erworbenen Kenntnisse sind geeignete Nachweise vorzulegen; dazu zählen insbesondere Falllisten, die regelmäßig folgende Angaben enthalten müssen: Akten- oder Geschäftszeichen, Gegenstand, Zeitraum, Art und Umfang der Tätigkeit, Sachstand. Ferner sind auf Verlangen der Prüfungsstelle anonymisierte Arbeitsproben vorzulegen.</P></Content>  </text></textdaten></norm>
<norm builddate="20161007120716" doknr="BJNR170700004BJNE003101118"><metadaten><jurabk>WiPrPrüfV</jurabk><enbez>§ 29</enbez><titel format="XML">Schriftliche Prüfung</titel></metadaten><textdaten><text format="XML"><Content><P>(1) Die schriftliche Prüfung besteht aus zwei unter Aufsicht anzufertigenden Arbeiten (Aufsichtsarbeiten). Die Aufgaben für die Aufsichtsarbeiten sind aus der Berufsarbeit der Wirtschaftsprüfer und Wirtschaftsprüferinnen zu entnehmen; die zuständigen Kommissionen sind die nach den §§ 8 und 9.</P><P>(2) Für jede Aufsichtsarbeit stehen vier bis sechs Stunden zur Verfügung. Behinderten Menschen kann die Frist verlängert werden; Hilfsmittel und die Inanspruchnahme von Hilfeleistungen Dritter, die die besonderen Verhältnisse behinderter Menschen berücksichtigen, sollen von der Prüfungsstelle zugelassen werden. Es sind zu bearbeiten je eine Aufgabe aus dem Gebiet des Wirtschaftsrechts (§ 27 Absatz 1 Nummer 1) und des Steuerrechts I (§ 27 Absatz 1 Nummer 2), und zwar jeweils eine Aufgabe an je einem Tag. Für die Aufgaben können zwei Themen zur Wahl gestellt werden. § 10 gilt entsprechend.</P><P>(3) Jede Aufsichtsarbeit ist von zwei nach § 26 Abs. 2 berufenen Mitgliedern der Prüfungskommission, die nicht an der mündlichen Prüfung teilnehmen müssen, selbstständig mit &quot;genügt den Anforderungen&quot; oder &quot;genügt nicht den Anforderungen&quot; zu bewerten. Die beiden Bewertungen können gegenseitig mitgeteilt werden. Eine nicht abgegebene Arbeit ist mit &quot;genügt nicht den Anforderungen&quot; zu bewerten. Die bei der mündlichen Prüfung mitwirkenden Mitglieder der Prüfungskommission haben das Recht, die Arbeit einzusehen. Weichen die Bewertungen einer Arbeit voneinander ab und einigen sich die beiden die Arbeit bewertenden Personen nicht, so ist die Arbeit zusätzlich durch ein Mitglied der Prüfungskommission, das nicht an der mündlichen Prüfung teilnehmen muss und von der Prüfungsstelle bestimmt wird, zu bewerten. Die Aufsichtsarbeit genügt in diesem Fall den Anforderungen, wenn mindestens zwei der die Arbeit bewertenden Personen die Arbeit so bewerten.</P></Content></text><fussnoten/></textdaten></norm>
<norm builddate="20161007120716" doknr="BJNR170700004BJNE003201118"><metadaten><jurabk>WiPrPrüfV</jurabk><enbez>§ 30</enbez><titel format="XML">Mündliche Prüfung</titel></metadaten><textdaten><text format="XML"><Content><P>(1) Die zu prüfende Person ist von der mündlichen Prüfung ausgeschlossen, wenn beide Aufsichtsarbeiten den Anforderungen nicht genügen; gleiches gilt, wenn in Fällen des § 28 eine Aufsichtsarbeit den Anforderungen nicht genügt. Die Prüfung ist nicht bestanden.</P><P>(2) Vor Beginn der mündlichen Prüfung findet eine Vorberatung der Prüfungskommission statt, zu der sämtliche Prüfungsunterlagen vorliegen.</P><P>(3) In der mündlichen Prüfung sind aus den in § 27 Abs. 2 genannten Prüfungsgebieten Fragen zu stellen, die mit der Berufsarbeit der Wirtschaftsprüfer und Wirtschaftsprüferinnen zusammenhängen.</P><P>(4) Die Dauer der Prüfung soll für die einzelne zu prüfende Person eine Stunde nicht überschreiten. Ist ein Prüfungsgebiet nach § 27 Abs. 2 Satz 2 zusätzlich Gegenstand der mündlichen Prüfung, so soll die Dauer der zusätzlichen mündlichen Prüfung in diesem Fach eine halbe Stunde nicht überschreiten. § 15 Abs. 3 Satz 3 und Abs. 4 gilt entsprechend.</P><P>(5) Zur Prüfung zugelassenen Personen sowie Personen, die mindestens vier Jahre im wirtschaftlichen Prüfungswesen tätig sind und ein berechtigtes Interesse glaubhaft machen, kann auf Antrag gestattet werden, einmal bei der mündlichen Prüfung zuzuhören.</P><P>(6) Die Bewertung der mündlichen Prüfungsleistungen mit &quot;genügt den Anforderungen&quot; oder &quot;genügt nicht den Anforderungen&quot; erfolgt auf Vorschlag der jeweils prüfenden Person durch die Prüfungskommission.</P><P>(7) Über den Hergang der mündlichen Prüfung ist eine Niederschrift aufzunehmen, in der festgestellt werden <DL Font="normal" Type="arabic"><DT>1.</DT><DD Font="normal"><LA Size="normal">die Besetzung der Prüfungskommission;</LA></DD><DT>2.</DT><DD Font="normal"><LA Size="normal">die Bewertung der schriftlichen Arbeiten;</LA></DD><DT>3.</DT><DD Font="normal"><LA Size="normal">die Bewertung der mündlichen Prüfung;</LA></DD><DT>4.</DT><DD Font="normal"><LA Size="normal">die Entscheidung der Prüfungskommission über das Ergebnis der Prüfung.</LA></DD></DL>Die Niederschrift ist von der vorsitzenden Person der Prüfungskommission zu unterschreiben.</P></Content></text><fussnoten/></textdaten></norm>
<norm builddate="20161007120716" doknr="BJNR170700004BJNE003300000"><metadaten><jurabk>WiPrPrüfV</jurabk><enbez>§ 31</enbez><titel format="parat">Prüfungsergebnis</titel></metadaten><textdaten><text format="XML"><Content><P>Die Prüfungskommission entscheidet im Anschluss an die mündliche Prüfung auf Grund des Gesamteindrucks der in der schriftlichen und in der mündlichen Prüfung erbrachten Leistungen, ob die geprüfte Person über die nach § 131h Abs. 2 der Wirtschaftsprüferordnung erforderlichen Kenntnisse verfügt und damit die Prüfung bestanden hat. § 18 Abs. 2 und 3 gilt entsprechend.</P></Content></text></textdaten></norm>
<norm builddate="20161007120716" doknr="BJNR170700004BJNE003400000"><metadaten><jurabk>WiPrPrüfV</jurabk><enbez>§ 32</enbez><titel format="parat">Rücktritt von der Prüfung</titel></metadaten><textdaten><text format="XML"><Content><P>Tritt die zu prüfende Person von der Prüfung zurück, so gilt die gesamte Prüfung als nicht bestanden. Als Rücktritt gilt es, wenn sie an einer Aufsichtsarbeit nicht teilnimmt oder sich der mündlichen Prüfung oder Teilen derselben nicht unterzieht. § 21 Abs. 2 und 3 gilt entsprechend.</P></Content></text></textdaten></norm>
<norm builddate="20161007120716" doknr="BJNR170700004BJNE003501118"><metadaten><jurabk>WiPrPrüfV</jurabk><enbez>§ 33</enbez><titel format="XML">Wiederholung der Prüfung</titel></metadaten><textdaten><text format="XML"><Content><P>(1) Die Prüfung kann zweimal wiederholt werden. Für die Wiederholung der Prüfung ist eine erneute Zulassung erforderlich.</P><P>(2) Wird der Antrag auf erneute Zulassung gestellt, sind nur die in § 25 Absatz 2 Nummer 1, 4, 5, 7 und 8 genannten Unterlagen und Erklärungen beizufügen.</P></Content></text><fussnoten/></textdaten></norm>
<norm builddate="20161007120716" doknr="BJNR170700004BJNE003600000"><metadaten><jurabk>WiPrPrüfV</jurabk><enbez>§ 34</enbez><titel format="parat">Täuschungsversuch, Ordnungsverstöße</titel></metadaten><textdaten><text format="XML"><Content><P>Unternimmt es eine zu prüfende Person, das Ergebnis einer schriftlichen Arbeit durch Täuschung oder Benutzung nicht zugelassener Hilfsmittel zu beeinflussen, so kann die Prüfungskommission die Arbeit mit &quot;genügt nicht den Anforderungen&quot; bewerten oder in schweren Fällen den Bewerber von der Prüfung ausschließen. Satz 1 gilt entsprechend für die mündliche Prüfung. § 24 Abs. 2 bis 4 gilt entsprechend.</P></Content></text></textdaten></norm>
<norm builddate="20161007120716" doknr="BJNR170700004BJNE003701118"><metadaten><jurabk>WiPrPrüfV</jurabk><enbez>§ 35</enbez><titel format="XML">Einsicht in Prüfungsakten</titel></metadaten><textdaten><text format="XML"><Content><P>Die geprüfte Person kann nach Bekanntgabe des Ergebnisses der Prüfung die Prüfungsakten persönlich einsehen.</P></Content></text><fussnoten/></textdaten></norm>
</dokumente>